papers_feed/arxiv_client.py
papers_feed/asset_manager.py
papers_feed/github_client.py
papers_feed/markdown_service.py
papers_feed/models.py
papers_feed/pandoc_utils.py
papers_feed/paper_manager.py
papers_feed/process_events.py
papers_feed/tex_utils.py
papers_feed/frontend/__init__.py
papers_feed/frontend/generate_html.py
papers_feed-0.1.0.dist-info/LICENSE
papers_feed-0.1.0.dist-info/METADATA
papers_feed-0.1.0.dist-info/WHEEL
papers_feed-0.1.0.dist-info/top_level.txt
papers_feed-0.1.0.dist-info/RECORD
