Metadata-Version: 2.1
Name: papers_feed
Version: 0.1.0
License: MIT License
Requires-Python: >=3.11
License-File: LICENSE
Requires-Dist: pyyaml
Requires-Dist: llamero>=0.2.5
Requires-Dist: aiohttp
Requires-Dist: pydantic
Requires-Dist: requests
Provides-Extra: test
Requires-Dist: pytest>=7.0; extra == "test"
Requires-Dist: pytest-cov>=4.0; extra == "test"
Requires-Dist: pytest-asyncio; extra == "test"
